dotdict_bench/__init__.py
dotdict_bench/__main__.py
dotdict_bench/apis.py
dotdict_bench/cases.py
dotdict_bench/sets.py
dotdict_bench/utils.py
dotdict_bench-0.0.0.dist-info/WHEEL
dotdict_bench-0.0.0.dist-info/METADATA
dotdict_bench-0.0.0.dist-info/RECORD
