Metadata-Version: 2.1
Name: dotdict-bench
Version: 0.0.0
Summary: Benchmarking for dot-accessible dict packages in python
License: MIT
Author: pwwang
Author-email: pwwang@pwwang.com
Requires-Python: >=3.9,<4.0
Classifier: License :: OSI Approved :: MIT License
Classifier: Programming Language :: Python :: 3
Classifier: Programming Language :: Python :: 3.9
Classifier: Programming Language :: Python :: 3.10
Requires-Dist: PyGithub (>=1.55,<2.0)
Requires-Dist: addict (>=2.4.0,<3.0.0)
Requires-Dist: benchwork (>=0.0.1,<0.0.2)
Requires-Dist: dictlib (>=1.1.5,<2.0.0)
Requires-Dist: diot (>=0.1.6,<0.2.0)
Requires-Dist: dotmap (>=1.3.30,<2.0.0)
Requires-Dist: dotsi (>=0.0.3,<0.0.4)
Requires-Dist: dotwiz (>=0.4.0,<0.5.0)
Requires-Dist: easydict (>=1.9,<2.0)
Requires-Dist: importlib-metadata (>=4.12.0,<5.0.0)
Requires-Dist: pyparam (>=0.5.3,<0.6.0)
Requires-Dist: python-box (>=6.0.2,<7.0.0)
